crimson/tracer_beta/__init__.py
crimson/tracer_beta/filter.py
crimson/tracer_beta/node.py
crimson/tracer_beta/tracer.py
crimson/tracer_beta/example/script.py
crimson_tracer_beta-0.1.3.dist-info/METADATA
crimson_tracer_beta-0.1.3.dist-info/WHEEL
crimson_tracer_beta-0.1.3.dist-info/top_level.txt
crimson_tracer_beta-0.1.3.dist-info/RECORD
